__init__.py
main.py
models.py
text_generation.py
demo_uv_tooling-0.3.0.dist-info/METADATA
demo_uv_tooling-0.3.0.dist-info/WHEEL
demo_uv_tooling-0.3.0.dist-info/top_level.txt
demo_uv_tooling-0.3.0.dist-info/RECORD
