Metadata-Version: 2.2
Name: demo_uv_tooling
Version: 0.3.0
Summary: Demonstrates the modern Python tooling with uv.
Requires-Python: >=3.12
Requires-Dist: accelerate>=1.2.1
Requires-Dist: fastapi[async,standard]>=0.115.6
Requires-Dist: httpx[async]>=0.28.1
Requires-Dist: mypy[pytest]>=1.14.1
Requires-Dist: pydantic>=2.10.4
Requires-Dist: pytest-asyncio>=0.25.1
Requires-Dist: torch>=2.5.1
Requires-Dist: transformers>=4.47.1
Requires-Dist: trio>=0.28.0
Requires-Dist: uv>=0.5.15
Requires-Dist: uvicorn>=0.34.0
